odoo10_addon_website_sale_checkout_country_vat-10.0.1.1.0-py2.7-nspkg.pth
odoo/addons/website_sale_checkout_country_vat/README.rst
odoo/addons/website_sale_checkout_country_vat/__init__.py
odoo/addons/website_sale_checkout_country_vat/__manifest__.py
odoo/addons/website_sale_checkout_country_vat/i18n/es.po
odoo/addons/website_sale_checkout_country_vat/static/description/icon.png
odoo/addons/website_sale_checkout_country_vat/static/src/js/dropdown.js
odoo/addons/website_sale_checkout_country_vat/views/assets.xml
odoo/addons/website_sale_checkout_country_vat/views/templates.xml
odoo10_addon_website_sale_checkout_country_vat-10.0.1.1.0.dist-info/DESCRIPTION.rst
odoo10_addon_website_sale_checkout_country_vat-10.0.1.1.0.dist-info/METADATA
odoo10_addon_website_sale_checkout_country_vat-10.0.1.1.0.dist-info/RECORD
odoo10_addon_website_sale_checkout_country_vat-10.0.1.1.0.dist-info/WHEEL
odoo10_addon_website_sale_checkout_country_vat-10.0.1.1.0.dist-info/metadata.json
odoo10_addon_website_sale_checkout_country_vat-10.0.1.1.0.dist-info/namespace_packages.txt
odoo10_addon_website_sale_checkout_country_vat-10.0.1.1.0.dist-info/top_level.txt
